tofuref/__init__.py
tofuref/config.py
tofuref/main.py
tofuref/tofuref.tcss
tofuref/data/bookmarks.py
tofuref/data/cache.py
tofuref/data/emojis.py
tofuref/data/helpers.py
tofuref/data/meta.py
tofuref/data/providers.py
tofuref/data/resources.py
tofuref/fallback/providers.json
tofuref/widgets/__init__.py
tofuref/widgets/code_block_select.py
tofuref/widgets/content_window.py
tofuref/widgets/keybindings.py
tofuref/widgets/logo.py
tofuref/widgets/menu_option_list_base.py
tofuref/widgets/providers_option_list.py
tofuref/widgets/resources_option_list.py
tofuref/widgets/search_input.py
tofuref/widgets/start_progress.py
tofuref/widgets/status.py
tofuref-1.7.0.dist-info/METADATA
tofuref-1.7.0.dist-info/WHEEL
tofuref-1.7.0.dist-info/entry_points.txt
tofuref-1.7.0.dist-info/licenses/LICENSE
tofuref-1.7.0.dist-info/RECORD
