Metadata-Version: 2.4
Name: tofuref
Version: 1.7.0
Summary: TUI for OpenTofu provider registry.
Project-URL: Homepage, https://github.com/DJetelina/tofuref
Project-URL: Repository, https://github.com/DJetelina/tofuref.git
Project-URL: Issues, https://github.com/DJetelina/tofuref/issues
Author: David Jetelina
License-Expression: MIT
License-File: LICENSE
Keywords: infra,opentofu,platform,sre,terraform,tofu,tool,tui
Classifier: Development Status :: 5 - Production/Stable
Classifier: Environment :: Console
Classifier: Intended Audience :: Developers
Classifier: Intended Audience :: System Administrators
Classifier: Programming Language :: Python :: 3
Classifier: Programming Language :: Python :: 3.10
Classifier: Programming Language :: Python :: 3.11
Classifier: Programming Language :: Python :: 3.12
Classifier: Programming Language :: Python :: 3.13
Classifier: Programming Language :: Python :: 3.14
Classifier: Topic :: Software Development
Classifier: Topic :: Software Development :: Documentation
Classifier: Topic :: Software Development :: User Interfaces
Classifier: Topic :: System :: Installation/Setup
Classifier: Topic :: System :: Systems Administration
Classifier: Topic :: Utilities
Requires-Python: >=3.10
Requires-Dist: anyio>=4.12.1
Requires-Dist: httpx>=0.28.1
Requires-Dist: packaging>=25.0
Requires-Dist: platformdirs>=4.5.1
Requires-Dist: python-frontmatter>=1.1.0
Requires-Dist: textual>=7.3.0
Requires-Dist: tomli>=2.2.1; python_full_version < '3.11'
Requires-Dist: yaucl>=0.2.0
